nthBday/__init__.py
nthBday/nthBday.py
nthBday-0.2.7.dist-info/LICENSE.txt
nthBday-0.2.7.dist-info/METADATA
nthBday-0.2.7.dist-info/WHEEL
nthBday-0.2.7.dist-info/top_level.txt
nthBday-0.2.7.dist-info/RECORD
