Metadata-Version: 2.1
Name: nthBday
Version: 0.2.7
Summary: An open-source python package to find business days of a month.
Home-page: https://github.com/U77w41/nthBday
Author: Ujjwal Chowdhury
Author-email: <u77w41@gmail.com>
License: MIT
Keywords: python,date,Business Day,Working Day,Holiday,calender
License-File: LICENSE.txt
Requires-Dist: pandas
Requires-Dist: datetime
